idun_guardian_client/.gitignore
idun_guardian_client/__init__.py
idun_guardian_client/__main__.py
idun_guardian_client/client.py
idun_guardian_client/config.py
idun_guardian_client/debug_logs.py
idun_guardian_client/igeb_api.py
idun_guardian_client/igeb_bluetooth.py
idun_guardian_client/igeb_metadata.py
idun_guardian_client/igeb_utils.py
idun_guardian_client/mock_utils.py
idun_guardian_client/test_producer_consumer.py
idun_guardian_client-1.5.0.dist-info/METADATA
idun_guardian_client-1.5.0.dist-info/WHEEL
idun_guardian_client-1.5.0.dist-info/RECORD
