Metadata-Version: 2.1
Name: idun-guardian-client
Version: 1.5.0
Summary: Python SDK for communication with the IDUN Guardian earbuds and IDUN cloud
Author: IDUN Technologies
Author-email: contact@iduntechnologies.com
Requires-Python: >=3.10,<4.0
Classifier: Programming Language :: Python :: 3
Classifier: Programming Language :: Python :: 3.10
Classifier: Programming Language :: Python :: 3.11
Classifier: Programming Language :: Python :: 3.12
Requires-Dist: bleak (==0.20.1)
Requires-Dist: httpx (>=0.24.1,<0.25.0)
Requires-Dist: idun-data-models (>=0.3.7,<0.4.0)
Requires-Dist: numpy (>=1.23,<2.0)
Requires-Dist: orjson (>=3.9,<4.0)
Requires-Dist: pycryptodome (>=3.15,<4.0)
Requires-Dist: pydantic (>=1.10,<2.0)
Requires-Dist: python-dotenv (>=0.21.0,<0.22.0)
Requires-Dist: requests (>=2.28,<3.0)
Requires-Dist: websockets (>=10.3,<11.0)
